vanguard/__init__.py
vanguard/_bibliography.py
vanguard/features.py
vanguard/kernels.py
vanguard/learning.py
vanguard/models.py
vanguard/normalise.py
vanguard/py.typed
vanguard/standardise.py
vanguard/uncertainty.py
vanguard/utils.py
vanguard/vanilla.py
vanguard/warnings.py
vanguard/base/__init__.py
vanguard/base/basecontroller.py
vanguard/base/gpcontroller.py
vanguard/base/metaclass.py
vanguard/base/metrics.py
vanguard/base/standardise.py
vanguard/base/posteriors/__init__.py
vanguard/base/posteriors/collection.py
vanguard/base/posteriors/posterior.py
vanguard/classification/__init__.py
vanguard/classification/binary.py
vanguard/classification/categorical.py
vanguard/classification/dirichlet.py
vanguard/classification/kernel.py
vanguard/classification/likelihoods.py
vanguard/classification/mixin.py
vanguard/classification/models.py
vanguard/datasets/__init__.py
vanguard/datasets/air_passengers.py
vanguard/datasets/basedataset.py
vanguard/datasets/bike.py
vanguard/datasets/classification.py
vanguard/datasets/synthetic.py
vanguard/datasets/data/air_passengers.csv
vanguard/datasets/data/bike.csv
vanguard/datasets/data/data_citations.rst
vanguard/decoratorutils/__init__.py
vanguard/decoratorutils/basedecorator.py
vanguard/decoratorutils/errors.py
vanguard/decoratorutils/wrapping.py
vanguard/distribute/__init__.py
vanguard/distribute/aggregators.py
vanguard/distribute/decorator.py
vanguard/distribute/partitioners.py
vanguard/hierarchical/__init__.py
vanguard/hierarchical/base.py
vanguard/hierarchical/collection.py
vanguard/hierarchical/distributions.py
vanguard/hierarchical/hyperparameter.py
vanguard/hierarchical/laplace.py
vanguard/hierarchical/module.py
vanguard/hierarchical/variational.py
vanguard/multitask/__init__.py
vanguard/multitask/decorator.py
vanguard/multitask/kernel.py
vanguard/multitask/likelihoods.py
vanguard/multitask/models.py
vanguard/optimise/__init__.py
vanguard/optimise/finder.py
vanguard/optimise/optimiser.py
vanguard/optimise/schedule.py
vanguard_gp-3.1.0.dist-info/licenses/LICENSE.md
vanguard_gp-3.1.0.dist-info/METADATA
vanguard_gp-3.1.0.dist-info/WHEEL
vanguard_gp-3.1.0.dist-info/top_level.txt
vanguard_gp-3.1.0.dist-info/RECORD
