Metadata-Version: 2.4
Name: vanguard-gp
Version: 3.1.0
Summary: Various easy-to-use extensions for Gaussian process models and a framework for composition of extensions.
Author-email: GCHQ <oss@gchq.gov.uk>
License: # GNU GENERAL PUBLIC LICENSE
Project-URL: Documentation, https://vanguard.readthedocs.io/en/latest/
Project-URL: Repository, https://github.com/gchq/Vanguard
Project-URL: Issues, https://github.com/gchq/Vanguard/issues
Project-URL: Changelog, https://github.com/gchq/Vanguard/blob/main/CHANGELOG.md
Keywords: gaussian-process,pytorch
Classifier: Development Status :: 4 - Beta
Classifier: License :: OSI Approved :: GNU General Public License v3 (GPLv3)
Classifier: Programming Language :: Python
Classifier: Programming Language :: Python :: 3.9
Classifier: Programming Language :: Python :: 3.10
Classifier: Programming Language :: Python :: 3.11
Classifier: Programming Language :: Python :: 3.12
Classifier: Programming Language :: Python :: 3.13
Classifier: Typing :: Typed
Requires-Python: >=3.9
License-File: LICENSE.md
Requires-Dist: bibtexparser>=1.1
Requires-Dist: gpytorch>=1.11
Requires-Dist: kmedoids>=0.3.3
Requires-Dist: kmedoids>=0.4; python_version >= "3.11"
Requires-Dist: kmedoids>=0.4.4; python_version >= "3.12"
Requires-Dist: kmedoids>=0.5.3; python_version >= "3.13"
Requires-Dist: matplotlib>=3.8.4
Requires-Dist: numpy>=2
Requires-Dist: numpy>=2.1.0; python_version >= "3.13"
Requires-Dist: pandas>=2
Requires-Dist: pandas>=2.2.3; python_version >= "3.13"
Requires-Dist: scikit-learn>=1.5.0
Requires-Dist: scikit-learn>=1.6.0; python_version >= "3.13"
Requires-Dist: scipy>=1.13
Requires-Dist: scipy>=1.14.1; python_version >= "3.13"
Requires-Dist: torch>=2.6
Requires-Dist: typing_extensions>=4.12
Requires-Dist: urllib3>=2.0.4
Provides-Extra: test
Requires-Dist: ipykernel>=6; extra == "test"
Requires-Dist: nbconvert>=7; extra == "test"
Requires-Dist: nbformat>=5; extra == "test"
Requires-Dist: tqdm>=4; extra == "test"
Requires-Dist: pytest-beartype>=0.1; extra == "test"
Requires-Dist: pytest-cov>=5; extra == "test"
Requires-Dist: pytest>=8.3.3; extra == "test"
Requires-Dist: beartype>=0.19; extra == "test"
Provides-Extra: doc
Requires-Dist: furo>=2024; extra == "doc"
Requires-Dist: ipykernel>=6; extra == "doc"
Requires-Dist: ipython>=8; extra == "doc"
Requires-Dist: nbconvert>=7; extra == "doc"
Requires-Dist: nbconvert>=7.1; python_version >= "3.11" and extra == "doc"
Requires-Dist: nbformat>=5; extra == "doc"
Requires-Dist: nbsphinx>=0.9; extra == "doc"
Requires-Dist: pillow>=10; extra == "doc"
Requires-Dist: pybtex>=0.24; extra == "doc"
Requires-Dist: setuptools>=75; python_version >= "3.12" and extra == "doc"
Requires-Dist: sphinx!=8.2.*,>=8; python_version >= "3.10" and extra == "doc"
Requires-Dist: sphinx!=8.2.*,>=7; python_version < "3.10" and extra == "doc"
Requires-Dist: sphinx-autodoc-typehints>=2; extra == "doc"
Requires-Dist: sphinxcontrib-bibtex>=2; extra == "doc"
Requires-Dist: tqdm>=4; extra == "doc"
Provides-Extra: notebook
Requires-Dist: jupyterlab>=4; extra == "notebook"
Requires-Dist: tqdm>=4; extra == "notebook"
Dynamic: license-file
